pyqt_loading_progressbar/__init__.py
pyqt_loading_progressbar/loadingProgressBar.py
pyqt_loading_progressbar-0.0.2.dist-info/LICENSE
pyqt_loading_progressbar-0.0.2.dist-info/METADATA
pyqt_loading_progressbar-0.0.2.dist-info/WHEEL
pyqt_loading_progressbar-0.0.2.dist-info/top_level.txt
pyqt_loading_progressbar-0.0.2.dist-info/RECORD
