Metadata-Version: 2.1
Name: pyqt-loading-progressbar
Version: 0.0.2
Summary: PyQt progress bar used for loading
Home-page: https://github.com/yjg30737/pyqt-loading-progressbar.git
Author: Jung Gyu Yoon
Author-email: yjg30737@gmail.com
License: MIT
Platform: UNKNOWN
License-File: LICENSE
Requires-Dist: PyQt5 (>=5.8)
